Workbook

Sheet Resumo Executivo
A1: RESUMO EXECUTIVO DE CUSTOS — SISTEMA NENC PROSÓDIA
A2: Cenário Projetado: 5.000 áudios/mês (2 min cada) = 10.000 minutos de processamento vocal
A4: 1. Principais Pilares da Arquitetura
A5: • Mensageria WhatsApp: | B5: Conversas iniciadas pelo usuário (Service Conversations) com 1.000 conversas grátis/mês.
A6: • Transcrição (STT): | B6: Whisper OpenAI ($0,006/min) ou Groq Whisper-large-v3-turbo ($0,00067/min).
A7: • Prosódia Vocal: | B7: DevAIce API para extração acústica de emoção, entonação e ritmo vocal.
A8: • Resumos Neuro / Dashboard: | B8: Modelos LLM rápidos e econômicos (GPT-4o-mini / Groq Llama 3.3).
A9: • Servidor & Infra: | B9: Docker Compose unificado (FastAPI + Streamlit + Caddy Proxy com SSL automático).
A10: • Retenção de Áudios: | B10: 7 dias de retenção automática, eliminando custos extras com cloud object storage.
A12: 2. Comparativo de Cenários Mensais (5.000 Áudios)
A14: Cenário | B14: Descrição do Setup | C14: Custo Mensal (USD) | D14: Custo Mensal (BRL) | E14: Custo / Áudio (BRL)
A15: Cenário Padrão | B15: OpenAI Whisper + DevAIce + Meta (1,4 áudio/conv) + VPS Hetzner | C15: ='Detalhamento Mensal (5k)'!E12 | D15: ='Detalhamento Mensal (5k)'!F12 | E15: ='Detalhamento Mensal (5k)'!F13
A16: Cenário Otimizado (Recomendado) | B16: Groq Whisper Turbo + DevAIce + Meta (2 áudios/conv) + VPS Hetzner | C16: ='Detalhamento Mensal (5k)'!G12 | D16: ='Detalhamento Mensal (5k)'!H12 | E16: ='Detalhamento Mensal (5k)'!H13
A17: Cenário Conservador (Teto) | B17: OpenAI Whisper + DevAIce ($0,015/min) + Meta (1 áudio/conv) + VPS Lightsail | C17: =120+150+60+4+20+1 | D17: =C17*'Premissas e Parâmetros'!B8 | E17: =D17/'Premissas e Parâmetros'!B5

Sheet Premissas e Parâmetros
A1: ESTIMATIVA DE CUSTOS — SISTEMA NENC PROSÓDIA & DASHBOARD
A2: Parâmetros e Variáveis de Base (Atualizáveis)
A4: Parâmetro | B4: Valor Base | C4: Unidade | D4: Descrição / Fonte de Referência
A5: Volume de Áudios por Mês | B5: 5000 | C5: áudios/mês | D5: Volume estimado de áudios recebidos dos clientes
A6: Duração Média do Áudio | B6: 2 | C6: minutos/áudio | D6: Tempo médio estimado por cada mensagem de voz
A7: Minutos Totais de Áudio / Mês | B7: =B5*B6 | C7: minutos/mês | D7: Total de minutos processados por mês (= Volume * Duração)
A8: Cotação do Dólar (USD -> BRL) | B8: 5.5 | C8: R$/USD | D8: Taxa de câmbio estimada para conversão em Reais
A9: Franquia Gratuita Meta WhatsApp | B9: 1000 | C9: conversas/mês | D9: 1.000 conversas de serviço gratuitas concedidas mensalmente pela Meta
A10: Tarifa Meta por Conversa de Serviço (BR) | B10: 0.03 | C10: USD/conversa | D10: Taxa Meta por janela de 24h iniciada pelo usuário no Brasil (~R$ 0,165)
A11: Tarifa Whisper OpenAI (whisper-1) | B11: 0.006 | C11: USD/minuto | D11: API OpenAI Whisper oficial ($0,006 por minuto de áudio)
A12: Tarifa Whisper Groq (whisper-large-v3-turbo) | B12: 0.00067 | C12: USD/minuto | D12: Groq Cloud Whisper Turbo (~$0,04 por hora)
A13: Tarifa Média DevAIce API | B13: 0.01 | C13: USD/minuto | D13: Estimativa de análise acústica/prosódica DevAIce por minuto
A14: Tarifa Média DevAIce API (Teto) | B14: 0.015 | C14: USD/minuto | D14: Cenário conservador de tarifa DevAIce por minuto
A15: Custo LLM por Áudio (GPT-4o-mini) | B15: 0.0005 | C15: USD/áudio | D15: Geração de resumo/insights neuromarketing via GPT-4o-mini
A16: Custo LLM por Áudio (GPT-4o padrão) | B16: 0.008 | C16: USD/áudio | D16: Geração de resumo/insights neuromarketing via GPT-4o padrão
A17: Custo Mensal VPS Hetzner CPX31 | B17: 12 | C17: USD/mês | D17: 4 vCPU / 8 GB RAM / 160 GB SSD (~€11/mês)
A18: Custo Mensal VPS AWS Lightsail | B18: 20 | C18: USD/mês | D18: 2 vCPU / 4 GB RAM / 80 GB SSD
A19: Custo Registro de Domínio | B19: 1 | C19: USD/mês | D19: Custo aproximado anual ($12/ano) dividido por 12 meses

Sheet Detalhamento Mensal (5k)
A1: DETALHAMENTO DE CUSTOS MENSAIS — VOLUME 5.000 ÁUDIOS (10.000 MINUTOS)
A2: Comparação detalhada por serviço: Padrão (OpenAI Whisper) vs Otimizado (Groq Whisper)
A4: Item / Serviço | B4: Provedor | C4: Base de Cálculo / Volume | D4: Preço Unitário (USD) | E4: Cenário Realista (USD) | F4: Cenário Realista (BRL) | G4: Cenário Otimizado (USD) | H4: Cenário Otimizado (BRL) | I4: Observações / Regras de Negócio
A5: WhatsApp Cloud API (Mensageria) | B5: Meta | C5: ~3.570 convs (1,4 áudios/conv) - 1.000 grátis = 2.570 pagas | D5: ='Premissas e Parâmetros'!B10 | E5: =2570*'Premissas e Parâmetros'!B10 | F5: =E5*'Premissas e Parâmetros'!B8 | G5: =1500*'Premissas e Parâmetros'!B10 | H5: =G5*'Premissas e Parâmetros'!B8 | I5: Usuário inicia. 1.000 conversas gratuitas/mês. Janela de 24h.
A6: Transcrição de Áudio (STT) | B6: OpenAI (Padrão) / Groq (Otimizado) | C6: 10.000 minutos de áudio / mês | D6: ='Premissas e Parâmetros'!B11 | E6: ='Premissas e Parâmetros'!B7*'Premissas e Parâmetros'!B11 | F6: =E6*'Premissas e Parâmetros'!B8 | G6: ='Premissas e Parâmetros'!B7*'Premissas e Parâmetros'!B12 | H6: =G6*'Premissas e Parâmetros'!B8 | I6: Padrão: OpenAI Whisper-1 ($0,006/min). Otimizado: Groq Turbo ($0,00067/min).
A7: Análise Prosódica / Emoção | B7: DevAIce API | C7: 10.000 minutos de áudio / mês | D7: ='Premissas e Parâmetros'!B13 | E7: ='Premissas e Parâmetros'!B7*'Premissas e Parâmetros'!B13 | F7: =E7*'Premissas e Parâmetros'!B8 | G7: ='Premissas e Parâmetros'!B7*'Premissas e Parâmetros'!B13 | H7: =G7*'Premissas e Parâmetros'!B8 | I7: Análise de tom, prosódia e acústica vocal.
A8: Geração de Insights & Resumos | B8: OpenAI / Groq (LLM) | C8: 5.000 requisições (prompts de síntese) | D8: ='Premissas e Parâmetros'!B15 | E8: ='Premissas e Parâmetros'!B5*'Premissas e Parâmetros'!B15 | F8: =E8*'Premissas e Parâmetros'!B8 | G8: ='Premissas e Parâmetros'!B5*'Premissas e Parâmetros'!B15 | H8: =G8*'Premissas e Parâmetros'!B8 | I8: Utilizando GPT-4o-mini para sumarização de métricas e neuro-relatórios.
A9: Hospedagem Servidor VPS | B9: Hetzner Cloud / Lightsail | C9: 1 Servidor Dedicado (Docker + API + Dashboard) | D9: ='Premissas e Parâmetros'!B17 | E9: ='Premissas e Parâmetros'!B17 | F9: =E9*'Premissas e Parâmetros'!B8 | G9: ='Premissas e Parâmetros'!B17 | H9: =G9*'Premissas e Parâmetros'!B8 | I9: Hetzner CPX31 (4 vCPU / 8 GB RAM) ou AWS Lightsail 4GB.
A10: Domínio, DNS & SSL | B10: Registro / Caddy / Cloudflare | C10: 1 Domínio + SSL automático Caddy | D10: ='Premissas e Parâmetros'!B19 | E10: ='Premissas e Parâmetros'!B19 | F10: =E10*'Premissas e Parâmetros'!B8 | G10: ='Premissas e Parâmetros'!B19 | H10: =G10*'Premissas e Parâmetros'!B8 | I10: SSL Let's Encrypt gratuito + Domínio (~$12/ano).
A11: Armazenamento de Áudios (Storage) | B11: Local VPS / Retenção 7 dias | C11: ~1,2 GB ativos no disco (rotação automática) | D11: 0 | E11: 0 | F11: =E11*'Premissas e Parâmetros'!B8 | G11: 0 | H11: =G11*'Premissas e Parâmetros'!B8 | I11: Política de expiração automática de 7 dias elimina necessidade de S3 pago.
A12: CUSTO TOTAL MENSAL | C12: 5.000 áudios (10.000 min) | E12: =SUM(E5:E11) | F12: =SUM(F5:F11) | G12: =SUM(G5:G11) | H12: =SUM(H5:H11) | I12: Economia mensal de ~R$ 440,00 no modelo otimizado!
A13: Custo Médio por Áudio (2 min) | C13: Unitário por áudio processado | E13: =E12/'Premissas e Parâmetros'!B5 | F13: =F12/'Premissas e Parâmetros'!B5 | G13: =G12/'Premissas e Parâmetros'!B5 | H13: =H12/'Premissas e Parâmetros'!B5 | I13: Custo final por áudio processado ponta a ponta

Sheet Simulação de Escala
A1: SIMULAÇÃO DE ESCALA DE CUSTOS (VOLUMES VARIADOS)
A2: Projeção de custos para diferentes faixas de uso mensal (Duração média: 2 min/áudio)
A4: Volume Mensal (Áudios) | B4: Minutos de Áudio | C4: Meta WhatsApp (USD) | D4: DevAIce API (USD) | E4: Whisper OpenAI (USD) | F4: Whisper Groq (USD) | G4: LLM Insights (USD) | H4: Hospedagem VPS (USD) | I4: Total Padrão (USD) | J4: Total Padrão (BRL) | K4: Total Otimizado (USD) | L4: Total Otimizado (BRL) | M4: Custo / Áudio (BRL)
A5: 1000 | B5: =A5*'Premissas e Parâmetros'!B6 | C5: =MAX(0, (A5/1.4 - 'Premissas e Parâmetros'!B9))*'Premissas e Parâmetros'!B10 | D5: =B5*'Premissas e Parâmetros'!B13 | E5: =B5*'Premissas e Parâmetros'!B11 | F5: =B5*'Premissas e Parâmetros'!B12 | G5: =A5*'Premissas e Parâmetros'!B15 | H5: 12 | I5: =C5+D5+E5+G5+H5+1 | J5: =I5*'Premissas e Parâmetros'!B8 | K5: =C5+D5+F5+G5+H5+1 | L5: =K5*'Premissas e Parâmetros'!B8 | M5: =L5/A5
A6: 2500 | B6: =A6*'Premissas e Parâmetros'!B6 | C6: =MAX(0, (A6/1.4 - 'Premissas e Parâmetros'!B9))*'Premissas e Parâmetros'!B10 | D6: =B6*'Premissas e Parâmetros'!B13 | E6: =B6*'Premissas e Parâmetros'!B11 | F6: =B6*'Premissas e Parâmetros'!B12 | G6: =A6*'Premissas e Parâmetros'!B15 | H6: 12 | I6: =C6+D6+E6+G6+H6+1 | J6: =I6*'Premissas e Parâmetros'!B8 | K6: =C6+D6+F6+G6+H6+1 | L6: =K6*'Premissas e Parâmetros'!B8 | M6: =L6/A6
A7: 5000 | B7: =A7*'Premissas e Parâmetros'!B6 | C7: =MAX(0, (A7/1.4 - 'Premissas e Parâmetros'!B9))*'Premissas e Parâmetros'!B10 | D7: =B7*'Premissas e Parâmetros'!B13 | E7: =B7*'Premissas e Parâmetros'!B11 | F7: =B7*'Premissas e Parâmetros'!B12 | G7: =A7*'Premissas e Parâmetros'!B15 | H7: 12 | I7: =C7+D7+E7+G7+H7+1 | J7: =I7*'Premissas e Parâmetros'!B8 | K7: =C7+D7+F7+G7+H7+1 | L7: =K7*'Premissas e Parâmetros'!B8 | M7: =L7/A7
A8: 10000 | B8: =A8*'Premissas e Parâmetros'!B6 | C8: =MAX(0, (A8/1.4 - 'Premissas e Parâmetros'!B9))*'Premissas e Parâmetros'!B10 | D8: =B8*'Premissas e Parâmetros'!B13 | E8: =B8*'Premissas e Parâmetros'!B11 | F8: =B8*'Premissas e Parâmetros'!B12 | G8: =A8*'Premissas e Parâmetros'!B15 | H8: 24 | I8: =C8+D8+E8+G8+H8+1 | J8: =I8*'Premissas e Parâmetros'!B8 | K8: =C8+D8+F8+G8+H8+1 | L8: =K8*'Premissas e Parâmetros'!B8 | M8: =L8/A8
A9: 20000 | B9: =A9*'Premissas e Parâmetros'!B6 | C9: =MAX(0, (A9/1.4 - 'Premissas e Parâmetros'!B9))*'Premissas e Parâmetros'!B10 | D9: =B9*'Premissas e Parâmetros'!B13 | E9: =B9*'Premissas e Parâmetros'!B11 | F9: =B9*'Premissas e Parâmetros'!B12 | G9: =A9*'Premissas e Parâmetros'!B15 | H9: 24 | I9: =C9+D9+E9+G9+H9+1 | J9: =I9*'Premissas e Parâmetros'!B8 | K9: =C9+D9+F9+G9+H9+1 | L9: =K9*'Premissas e Parâmetros'!B8 | M9: =L9/A9
A10: 50000 | B10: =A10*'Premissas e Parâmetros'!B6 | C10: =MAX(0, (A10/1.4 - 'Premissas e Parâmetros'!B9))*'Premissas e Parâmetros'!B10 | D10: =B10*'Premissas e Parâmetros'!B13 | E10: =B10*'Premissas e Parâmetros'!B11 | F10: =B10*'Premissas e Parâmetros'!B12 | G10: =A10*'Premissas e Parâmetros'!B15 | H10: 48 | I10: =C10+D10+E10+G10+H10+1 | J10: =I10*'Premissas e Parâmetros'!B8 | K10: =C10+D10+F10+G10+H10+1 | L10: =K10*'Premissas e Parâmetros'!B8 | M10: =L10/A10
